{
  "record_count": 435,
  "records": [
    {
      "conditions": [],
      "genes": [],
      "manufacturer_or_lab": "Advy Chemical Pvt Ltd.",
      "marker": "Malaria",
      "name": "AdvDx Malaria Pf Rapid Malaria Ag Detection Test",
      "prequalification_year": "2019",
      "region": "who",
      "regulatory_version": "Rest-of-World",
      "source": "who_ivd",
      "source_id": "00-DKM-RK-MALADX- 004-001",
      "test_category": "Immunochromatographic (lateral flow)"
    },
    {
      "conditions": [],
      "genes": [],
      "manufacturer_or_lab": "Advy Chemical Pvt Ltd.",
      "marker": "Malaria",
      "name": "AdvDx Malaria Pf Rapid Malaria Ag Detection Test",
      "prequalification_year": "2019",
      "region": "who",
      "regulatory_version": "Rest-of-World",
      "source": "who_ivd",
      "source_id": "00-DKM-RK-MALADX- 004-001-010",
      "test_category": "Immunochromatographic (lateral flow)"
    },
    {
      "conditions": [],
      "genes": [],
      "manufacturer_or_lab": "Advy Chemical Pvt Ltd.",
      "marker": "Malaria",
      "name": "AdvDx Malaria Pf Rapid Malaria Ag Detection Test",
      "prequalification_year": "2019",
      "region": "who",
      "regulatory_version": "Rest-of-World",
      "source": "who_ivd",
      "source_id": "00-DKM-RK-MALADX- 004-001-25",
      "test_category": "Immunochromatographic (lateral flow)"
    },
    {
      "conditions": [],
      "genes": [],
      "manufacturer_or_lab": "Advy Chemical Pvt Ltd.",
      "marker": "Malaria",
      "name": "AdvDx Malaria Pf Rapid Malaria Ag Detection Test",
      "prequalification_year": "2019",
      "region": "who",
      "regulatory_version": "Rest-of-World",
      "source": "who_ivd",
      "source_id": "00-DKMRK- MALADX- 004- 010",
      "test_category": "Immunochromatographic (lateral flow)"
    },
    {
      "conditions": [],
      "genes": [],
      "manufacturer_or_lab": "Advy Chemical Pvt Ltd.",
      "marker": "Malaria",
      "name": "AdvDx Malaria Pf Rapid Malaria Ag Detection Test",
      "prequalification_year": "2019",
      "region": "who",
      "regulatory_version": "Rest-of-World",
      "source": "who_ivd",
      "source_id": "00-DKMRK- MALADX- 004- 025",
      "test_category": "Immunochromatographic (lateral flow)"
    },
    {
      "conditions": [],
      "genes": [],
      "manufacturer_or_lab": "Advy Chemical Pvt Ltd.",
      "marker": "Malaria",
      "name": "AdvDx Malaria Pf Rapid Malaria Ag Detection Test",
      "prequalification_year": "2019",
      "region": "who",
      "regulatory_version": "Rest-of-World",
      "source": "who_ivd",
      "source_id": "00-DKMRK- MALADX- 004- 050",
      "test_category": "Immunochromatographic (lateral flow)"
    },
    {
      "conditions": [],
      "genes": [],
      "manufacturer_or_lab": "Abbott Diagnostics Korea Inc.",
      "marker": "HBV",
      "name": "Bioline HBsAg WB (formerly SD BIOLINE HBsAg WB)",
      "prequalification_year": "2017",
      "region": "who",
      "regulatory_version": "Rest-of-World",
      "source": "who_ivd",
      "source_id": "01FK10W",
      "test_category": "Immunochromatographic (lateral flow)"
    },
    {
      "conditions": [],
      "genes": [],
      "manufacturer_or_lab": "Roche Molecular Systems, Inc.",
      "marker": "HIV",
      "name": "COBAS AmpliPrep / COBAS TaqMan HIV-1 Test, version 2.0 (TaqMan 96)",
      "prequalification_year": "2012",
      "region": "who",
      "regulatory_version": "Directive 98/79/EC: Product design examination certificate, Annex IV.4",
      "source": "who_ivd",
      "source_id": "028127387001",
      "test_category": "NAT (nucleic acid testing)"
    },
    {
      "conditions": [],
      "genes": [],
      "manufacturer_or_lab": "Abbott Diagnostics Korea Inc.",
      "marker": "HCV",
      "name": "Bioline HCV (formerly SD BIOLINE HCV)",
      "prequalification_year": "2016",
      "region": "who",
      "regulatory_version": "Rest-of-World",
      "source": "who_ivd",
      "source_id": "02FK10",
      "test_category": "Immunochromatographic (lateral flow)"
    },
    {
      "conditions": [],
      "genes": [],
      "manufacturer_or_lab": "Abbott Diagnostics Korea Inc.",
      "marker": "HCV",
      "name": "Bioline HCV (formerly SD BIOLINE HCV)",
      "prequalification_year": "2016",
      "region": "who",
      "regulatory_version": "Rest-of-World",
      "source": "who_ivd",
      "source_id": "02FK16",
      "test_category": "Immunochromatographic (lateral flow)"
    },
    {
      "conditions": [],
      "genes": [],
      "manufacturer_or_lab": "Abbott Diagnostics Korea Inc.",
      "marker": "HCV",
      "name": "Bioline HCV (formerly SD BIOLINE HCV)",
      "prequalification_year": "2016",
      "region": "who",
      "regulatory_version": "Rest-of-World",
      "source": "who_ivd",
      "source_id": "02FK17",
      "test_category": "Immunochromatographic (lateral flow)"
    },
    {
      "conditions": [],
      "genes": [],
      "manufacturer_or_lab": "Abbott Molecular Inc.",
      "marker": "HIV",
      "name": "Abbott RealTime HIV-1 (m2000sp)",
      "prequalification_year": "2011",
      "region": "who",
      "regulatory_version": "Directive 98/79/EC: Product design examination certificate, Annex IV.4",
      "source": "who_ivd",
      "source_id": "02G31-010",
      "test_category": "NAT (nucleic acid testing)"
    },
    {
      "conditions": [],
      "genes": [
        "G6PD"
      ],
      "manufacturer_or_lab": "SD Biosensor, Inc.",
      "marker": "G6PD deficiency",
      "name": "STANDARD G6PD Test",
      "prequalification_year": "2024",
      "region": "who",
      "regulatory_version": "Directive 98/79/EC: Self-declared CE-mark, Annex III",
      "source": "who_ivd",
      "source_id": "02G6S11",
      "test_category": "Enzymatic"
    },
    {
      "conditions": [],
      "genes": [
        "G6PD"
      ],
      "manufacturer_or_lab": "SD Biosensor, Inc.",
      "marker": "G6PD deficiency",
      "name": "STANDARD G6PD Test",
      "prequalification_year": "2024",
      "region": "who",
      "regulatory_version": "Directive 98/79/EC: Self-declared CE-mark, Annex III",
      "source": "who_ivd",
      "source_id": "02G6S11A",
      "test_category": "Enzymatic"
    },
    {
      "conditions": [],
      "genes": [],
      "manufacturer_or_lab": "Abbott GmbH",
      "marker": "HPV",
      "name": "Abbott RealTime High Risk HPV",
      "prequalification_year": "2019",
      "region": "who",
      "regulatory_version": "Directive 98/79/EC: Self-declared CE-mark, Annex III",
      "source": "who_ivd",
      "source_id": "02N09-080",
      "test_category": "NAT (nucleic acid testing)"
    },
    {
      "conditions": [],
      "genes": [],
      "manufacturer_or_lab": "Abbott GmbH",
      "marker": "HPV",
      "name": "Abbott RealTime High Risk HPV",
      "prequalification_year": "2019",
      "region": "who",
      "regulatory_version": "Directive 98/79/EC: Self-declared CE-mark, Annex III",
      "source": "who_ivd",
      "source_id": "02N09-092",
      "test_category": "NAT (nucleic acid testing)"
    },
    {
      "conditions": [],
      "genes": [],
      "manufacturer_or_lab": "Roche Molecular Systems, Inc.",
      "marker": "HIV",
      "name": "COBAS AmpliPrep / COBAS TaqMan HIV-1 Test, version 2.0 (TaqMan 96)",
      "prequalification_year": "2012",
      "region": "who",
      "regulatory_version": "Directive 98/79/EC: Product design examination certificate, Annex IV.4",
      "source": "who_ivd",
      "source_id": "03051315001",
      "test_category": "NAT (nucleic acid testing)"
    },
    {
      "conditions": [],
      "genes": [],
      "manufacturer_or_lab": "Roche Molecular Systems, Inc.",
      "marker": "HIV",
      "name": "COBAS AmpliPrep / COBAS TaqMan HIV-1 Test, version 2.0 (TaqMan 96)",
      "prequalification_year": "2012",
      "region": "who",
      "regulatory_version": "Directive 98/79/EC: Product design examination certificate, Annex IV.4",
      "source": "who_ivd",
      "source_id": "03121453001",
      "test_category": "NAT (nucleic acid testing)"
    },
    {
      "conditions": [],
      "genes": [],
      "manufacturer_or_lab": "Roche Molecular Systems, Inc.",
      "marker": "HIV",
      "name": "COBAS AmpliPrep / COBAS TaqMan HIV-1 Test, version 2.0 (TaqMan 96)",
      "prequalification_year": "2012",
      "region": "who",
      "regulatory_version": "Directive 98/79/EC: Product design examination certificate, Annex IV.4",
      "source": "who_ivd",
      "source_id": "03587797190",
      "test_category": "NAT (nucleic acid testing)"
    },
    {
      "conditions": [],
      "genes": [],
      "manufacturer_or_lab": "Abbott Diagnostics Korea Inc.",
      "marker": "HIV",
      "name": "Bioline HIV1/2 3.0",
      "prequalification_year": "2013",
      "region": "who",
      "regulatory_version": "Rest-of-World",
      "source": "who_ivd",
      "source_id": "03FK10",
      "test_category": "Immunochromatographic (lateral flow)"
    },
    {
      "conditions": [],
      "genes": [],
      "manufacturer_or_lab": "Abbott Diagnostics Korea Inc.",
      "marker": "HIV",
      "name": "Bioline HIV1/2 3.0",
      "prequalification_year": "2013",
      "region": "who",
      "regulatory_version": "Rest-of-World",
      "source": "who_ivd",
      "source_id": "03FK16",
      "test_category": "Immunochromatographic (lateral flow)"
    },
    {
      "conditions": [],
      "genes": [],
      "manufacturer_or_lab": "Abbott Diagnostics Korea Inc.",
      "marker": "HIV",
      "name": "Bioline HIV1/2 3.0",
      "prequalification_year": "2013",
      "region": "who",
      "regulatory_version": "Rest-of-World",
      "source": "who_ivd",
      "source_id": "03FK17",
      "test_category": "Immunochromatographic (lateral flow)"
    },
    {
      "conditions": [],
      "genes": [],
      "manufacturer_or_lab": "Abbott Diagnostics Korea Inc.",
      "marker": "HIV",
      "name": "Bioline HIV1/2 3.0",
      "prequalification_year": "2013",
      "region": "who",
      "regulatory_version": "Rest-of-World",
      "source": "who_ivd",
      "source_id": "03FK22",
      "test_category": "Immunochromatographic (lateral flow)"
    },
    {
      "conditions": [],
      "genes": [],
      "manufacturer_or_lab": "Denka Seiken Co., LTD, Kagamida Factory",
      "marker": "HCV",
      "name": "ARCHITECT HCV Ag assay",
      "prequalification_year": "2019",
      "region": "who",
      "regulatory_version": "Directive 98/79/EC: Product design examination certificate, Annex IV.4",
      "source": "who_ivd",
      "source_id": "03M74-02",
      "test_category": "IA - Enzyme immunoassay EIA"
    },
    {
      "conditions": [],
      "genes": [],
      "manufacturer_or_lab": "Abbott Molecular Inc.",
      "marker": "HIV",
      "name": "Abbott RealTime HIV-1 (manual)",
      "prequalification_year": "2011",
      "region": "who",
      "regulatory_version": "Directive 98/79/EC: Product design examination certificate, Annex IV.4",
      "source": "who_ivd",
      "source_id": "04J70-24",
      "test_category": "NAT (nucleic acid testing)"
    },
    {
      "conditions": [],
      "genes": [],
      "manufacturer_or_lab": "Abbott Molecular Inc.",
      "marker": "HIV",
      "name": "Abbott RealTime HIV-1 (m2000sp)",
      "prequalification_year": "2011",
      "region": "who",
      "regulatory_version": "Directive 98/79/EC: Product design examination certificate, Annex IV.4",
      "source": "who_ivd",
      "source_id": "04J70-24",
      "test_category": "NAT (nucleic acid testing)"
    },
    {
      "conditions": [],
      "genes": [
        "CD4",
        "KIT"
      ],
      "manufacturer_or_lab": "Sysmex Partec GmbH",
      "marker": "HIV",
      "name": "CyFlow Counter System with CD4 easy count kit and CD4% easy count kit",
      "prequalification_year": "2018",
      "region": "who",
      "regulatory_version": "Directive 98/79/EC: Self-declared CE-mark, Annex III",
      "source": "who_ivd",
      "source_id": "05-8401",
      "test_category": "Flow cytometry"
    },
    {
      "conditions": [],
      "genes": [
        "CD4",
        "KIT"
      ],
      "manufacturer_or_lab": "Sysmex Partec GmbH",
      "marker": "HIV",
      "name": "CyFlow Counter System with CD4 easy count kit and CD4% easy count kit",
      "prequalification_year": "2018",
      "region": "who",
      "regulatory_version": "Directive 98/79/EC: Self-declared CE-mark, Annex III",
      "source": "who_ivd",
      "source_id": "05-8405",
      "test_category": "Flow cytometry"
    },
    {
      "conditions": [],
      "genes": [
        "CD4",
        "KIT"
      ],
      "manufacturer_or_lab": "Sysmex Partec GmbH",
      "marker": "HIV",
      "name": "CyFlow Counter System with CD4 easy count kit and CD4% easy count kit",
      "prequalification_year": "2018",
      "region": "who",
      "regulatory_version": "Directive 98/79/EC: Self-declared CE-mark, Annex III",
      "source": "who_ivd",
      "source_id": "05-8410",
      "test_category": "Flow cytometry"
    },
    {
      "conditions": [],
      "genes": [
        "CD4",
        "KIT"
      ],
      "manufacturer_or_lab": "Sysmex Partec GmbH",
      "marker": "HIV",
      "name": "CyFlow Counter System with CD4 easy count kit and CD4% easy count kit",
      "prequalification_year": "2018",
      "region": "who",
      "regulatory_version": "Directive 98/79/EC: Self-declared CE-mark, Annex III",
      "source": "who_ivd",
      "source_id": "05-8411",
      "test_category": "Flow cytometry"
    },
    {
      "conditions": [],
      "genes": [],
      "manufacturer_or_lab": "Roche Molecular Systems, Inc.",
      "marker": "HIV",
      "name": "COBAS AmpliPrep / COBAS TaqMan HIV-1 Test, version 2.0 (TaqMan 96)",
      "prequalification_year": "2012",
      "region": "who",
      "regulatory_version": "Directive 98/79/EC: Product design examination certificate, Annex IV.4",
      "source": "who_ivd",
      "source_id": "05212294190",
      "test_category": "NAT (nucleic acid testing)"
    },
    {
      "conditions": [],
      "genes": [],
      "manufacturer_or_lab": "Roche Molecular Systems, Inc.",
      "marker": "HPV",
      "name": "cobas 4800 HPV Test",
      "prequalification_year": "2024",
      "region": "who",
      "regulatory_version": "USFDA: Premarket Approval (PMA)",
      "source": "who_ivd",
      "source_id": "05235812190",
      "test_category": "NAT (nucleic acid testing)"
    },
    {
      "conditions": [],
      "genes": [],
      "manufacturer_or_lab": "Roche Molecular Systems, Inc.",
      "marker": "HPV",
      "name": "cobas 4800 HPV Test",
      "prequalification_year": "2024",
      "region": "who",
      "regulatory_version": "USFDA: Premarket Approval (PMA)",
      "source": "who_ivd",
      "source_id": "05235839190",
      "test_category": "NAT (nucleic acid testing)"
    },
    {
      "conditions": [],
      "genes": [],
      "manufacturer_or_lab": "Roche Molecular Systems, Inc.",
      "marker": "HPV",
      "name": "cobas 4800 HPV Test",
      "prequalification_year": "2024",
      "region": "who",
      "regulatory_version": "USFDA: Premarket Approval (PMA)",
      "source": "who_ivd",
      "source_id": "05235855190",
      "test_category": "NAT (nucleic acid testing)"
    },
    {
      "conditions": [],
      "genes": [],
      "manufacturer_or_lab": "Roche Molecular Systems, Inc.",
      "marker": "HPV",
      "name": "cobas 4800 HPV Test",
      "prequalification_year": "2024",
      "region": "who",
      "regulatory_version": "USFDA: Premarket Approval (PMA)",
      "source": "who_ivd",
      "source_id": "05235863190",
      "test_category": "NAT (nucleic acid testing)"
    },
    {
      "conditions": [],
      "genes": [],
      "manufacturer_or_lab": "Roche Molecular Systems, Inc.",
      "marker": "HPV",
      "name": "cobas 4800 HPV Test",
      "prequalification_year": "2024",
      "region": "who",
      "regulatory_version": "USFDA: Premarket Approval (PMA)",
      "source": "who_ivd",
      "source_id": "05235871190",
      "test_category": "NAT (nucleic acid testing)"
    },
    {
      "conditions": [],
      "genes": [],
      "manufacturer_or_lab": "Roche Molecular Systems, Inc.",
      "marker": "HPV",
      "name": "cobas 4800 HPV Test",
      "prequalification_year": "2024",
      "region": "who",
      "regulatory_version": "USFDA: Premarket Approval (PMA)",
      "source": "who_ivd",
      "source_id": "05235880190",
      "test_category": "NAT (nucleic acid testing)"
    },
    {
      "conditions": [],
      "genes": [],
      "manufacturer_or_lab": "Roche Molecular Systems, Inc.",
      "marker": "HPV",
      "name": "cobas 4800 HPV Test",
      "prequalification_year": "2024",
      "region": "who",
      "regulatory_version": "USFDA: Premarket Approval (PMA)",
      "source": "who_ivd",
      "source_id": "05235898190",
      "test_category": "NAT (nucleic acid testing)"
    },
    {
      "conditions": [],
      "genes": [],
      "manufacturer_or_lab": "Roche Molecular Systems, Inc.",
      "marker": "HPV",
      "name": "cobas 4800 HPV Test",
      "prequalification_year": "2024",
      "region": "who",
      "regulatory_version": "USFDA: Premarket Approval (PMA)",
      "source": "who_ivd",
      "source_id": "05235901190",
      "test_category": "NAT (nucleic acid testing)"
    },
    {
      "conditions": [],
      "genes": [],
      "manufacturer_or_lab": "Roche Molecular Systems, Inc.",
      "marker": "HPV",
      "name": "cobas 4800 HPV Test",
      "prequalification_year": "2024",
      "region": "who",
      "regulatory_version": "USFDA: Premarket Approval (PMA)",
      "source": "who_ivd",
      "source_id": "05235910190",
      "test_category": "NAT (nucleic acid testing)"
    },
    {
      "conditions": [],
      "genes": [],
      "manufacturer_or_lab": "Roche Molecular Systems, Inc.",
      "marker": "HIV",
      "name": "COBAS AmpliPrep / COBAS TaqMan HIV-1 Test, version 2.0 (TaqMan 96)",
      "prequalification_year": "2012",
      "region": "who",
      "regulatory_version": "Directive 98/79/EC: Product design examination certificate, Annex IV.4",
      "source": "who_ivd",
      "source_id": "05527503001",
      "test_category": "NAT (nucleic acid testing)"
    },
    {
      "conditions": [],
      "genes": [],
      "manufacturer_or_lab": "Roche Molecular Systems, Inc.",
      "marker": "HIV",
      "name": "COBAS AmpliPrep / COBAS TaqMan HIV-1 Test, version 2.0 (TaqMan 96)",
      "prequalification_year": "2012",
      "region": "who",
      "regulatory_version": "Directive 98/79/EC: Product design examination certificate, Annex IV.4",
      "source": "who_ivd",
      "source_id": "05807875001",
      "test_category": "NAT (nucleic acid testing)"
    },
    {
      "conditions": [],
      "genes": [],
      "manufacturer_or_lab": "Abbott Diagnostics Korea Inc.",
      "marker": "Malaria",
      "name": "Bioline Malaria Ag P.f/P.f/P.v (formerly SD BIOLINE Malaria Ag P.f/P.f/P.v)",
      "prequalification_year": "2018",
      "region": "who",
      "regulatory_version": "Directive 98/79/EC: Self-declared CE-mark, Annex III",
      "source": "who_ivd",
      "source_id": "05FK120",
      "test_category": "Immunochromatographic (lateral flow)"
    },
    {
      "conditions": [],
      "genes": [],
      "manufacturer_or_lab": "Abbott Diagnostics Korea Inc.",
      "marker": "Malaria",
      "name": "Bioline Malaria Ag P.f/P.f/P.v (formerly SD BIOLINE Malaria Ag P.f/P.f/P.v)",
      "prequalification_year": "2018",
      "region": "who",
      "regulatory_version": "Directive 98/79/EC: Self-declared CE-mark, Annex III",
      "source": "who_ivd",
      "source_id": "05FK123",
      "test_category": "Immunochromatographic (lateral flow)"
    },
    {
      "conditions": [],
      "genes": [],
      "manufacturer_or_lab": "Abbott Diagnostics Korea Inc.",
      "marker": "Malaria",
      "name": "NxTek Eliminate Malaria Pf and NxTek Malaria Pf",
      "prequalification_year": "2019",
      "region": "who",
      "regulatory_version": "Directive 98/79/EC: Self-declared CE-mark, Annex III",
      "source": "who_ivd",
      "source_id": "05FK140",
      "test_category": "Immunochromatographic (lateral flow)"
    },
    {
      "conditions": [],
      "genes": [],
      "manufacturer_or_lab": "Abbott Diagnostics Korea Inc.",
      "marker": "Malaria",
      "name": "NxTek Eliminate Malaria Pf and NxTek Malaria Pf",
      "prequalification_year": "2019",
      "region": "who",
      "regulatory_version": "Directive 98/79/EC: Self-declared CE-mark, Annex III",
      "source": "who_ivd",
      "source_id": "05FK141",
      "test_category": "Immunochromatographic (lateral flow)"
    },
    {
      "conditions": [],
      "genes": [],
      "manufacturer_or_lab": "Abbott Diagnostics Korea Inc.",
      "marker": "Malaria",
      "name": "NxTek Eliminate Malaria Pf and NxTek Malaria Pf",
      "prequalification_year": "2019",
      "region": "who",
      "regulatory_version": "Directive 98/79/EC: Self-declared CE-mark, Annex III",
      "source": "who_ivd",
      "source_id": "05FK142",
      "test_category": "Immunochromatographic (lateral flow)"
    },
    {
      "conditions": [],
      "genes": [],
      "manufacturer_or_lab": "Abbott Diagnostics Korea Inc.",
      "marker": "Malaria",
      "name": "NxTek Eliminate Malaria Pf and NxTek Malaria Pf",
      "prequalification_year": "2019",
      "region": "who",
      "regulatory_version": "Directive 98/79/EC: Self-declared CE-mark, Annex III",
      "source": "who_ivd",
      "source_id": "05FK143",
      "test_category": "Immunochromatographic (lateral flow)"
    },
    {
      "conditions": [],
      "genes": [],
      "manufacturer_or_lab": "Abbott Diagnostics Korea Inc.",
      "marker": "Malaria",
      "name": "NxTek Eliminate Malaria Pf and NxTek Malaria Pf",
      "prequalification_year": "2019",
      "region": "who",
      "regulatory_version": "Directive 98/79/EC: Self-declared CE-mark, Annex III",
      "source": "who_ivd",
      "source_id": "05FK144",
      "test_category": "Immunochromatographic (lateral flow)"
    },
    {
      "conditions": [],
      "genes": [],
      "manufacturer_or_lab": "Abbott Diagnostics Korea Inc.",
      "marker": "Malaria",
      "name": "Bioline Malaria Ag P.f",
      "prequalification_year": "2010",
      "region": "who",
      "regulatory_version": "Directive 98/79/EC: Self-declared CE-mark, Annex III",
      "source": "who_ivd",
      "source_id": "05FK50",
      "test_category": "Immunochromatographic (lateral flow)"
    },
    {
      "conditions": [],
      "genes": [],
      "manufacturer_or_lab": "Abbott Diagnostics Korea Inc.",
      "marker": "Malaria",
      "name": "Bioline Malaria Ag P.f",
      "prequalification_year": "2010",
      "region": "who",
      "regulatory_version": "Directive 98/79/EC: Self-declared CE-mark, Annex III",
      "source": "who_ivd",
      "source_id": "05FK51",
      "test_category": "Immunochromatographic (lateral flow)"
    },
    {
      "conditions": [],
      "genes": [],
      "manufacturer_or_lab": "Abbott Diagnostics Korea Inc.",
      "marker": "Malaria",
      "name": "Bioline Malaria Ag P.f",
      "prequalification_year": "2010",
      "region": "who",
      "regulatory_version": "Directive 98/79/EC: Self-declared CE-mark, Annex III",
      "source": "who_ivd",
      "source_id": "05FK52",
      "test_category": "Immunochromatographic (lateral flow)"
    },
    {
      "conditions": [],
      "genes": [],
      "manufacturer_or_lab": "Abbott Diagnostics Korea Inc.",
      "marker": "Malaria",
      "name": "Bioline Malaria Ag P.f",
      "prequalification_year": "2010",
      "region": "who",
      "regulatory_version": "Directive 98/79/EC: Self-declared CE-mark, Annex III",
      "source": "who_ivd",
      "source_id": "05FK53",
      "test_category": "Immunochromatographic (lateral flow)"
    },
    {
      "conditions": [],
      "genes": [],
      "manufacturer_or_lab": "Abbott Diagnostics Korea Inc.",
      "marker": "Malaria",
      "name": "Bioline Malaria Ag P.f/Pan",
      "prequalification_year": "2013",
      "region": "who",
      "regulatory_version": "Directive 98/79/EC: Self-declared CE-mark, Annex III",
      "source": "who_ivd",
      "source_id": "05FK60",
      "test_category": "Immunochromatographic (lateral flow)"
    },
    {
      "conditions": [],
      "genes": [],
      "manufacturer_or_lab": "Abbott Diagnostics Korea Inc.",
      "marker": "Malaria",
      "name": "Bioline Malaria Ag P.f/Pan",
      "prequalification_year": "2013",
      "region": "who",
      "regulatory_version": "Directive 98/79/EC: Self-declared CE-mark, Annex III",
      "source": "who_ivd",
      "source_id": "05FK61",
      "test_category": "Immunochromatographic (lateral flow)"
    },
    {
      "conditions": [],
      "genes": [],
      "manufacturer_or_lab": "Abbott Diagnostics Korea Inc.",
      "marker": "Malaria",
      "name": "Bioline Malaria Ag P.f/Pan",
      "prequalification_year": "2013",
      "region": "who",
      "regulatory_version": "Directive 98/79/EC: Self-declared CE-mark, Annex III",
      "source": "who_ivd",
      "source_id": "05FK62",
      "test_category": "Immunochromatographic (lateral flow)"
    },
    {
      "conditions": [],
      "genes": [],
      "manufacturer_or_lab": "Abbott Diagnostics Korea Inc.",
      "marker": "Malaria",
      "name": "Bioline Malaria Ag P.f/Pan",
      "prequalification_year": "2013",
      "region": "who",
      "regulatory_version": "Directive 98/79/EC: Self-declared CE-mark, Annex III",
      "source": "who_ivd",
      "source_id": "05FK63",
      "test_category": "Immunochromatographic (lateral flow)"
    },
    {
      "conditions": [],
      "genes": [],
      "manufacturer_or_lab": "Abbott Diagnostics Korea Inc.",
      "marker": "Malaria",
      "name": "Bioline Malaria Ag P.f/Pan",
      "prequalification_year": "2013",
      "region": "who",
      "regulatory_version": "Directive 98/79/EC: Self-declared CE-mark, Annex III",
      "source": "who_ivd",
      "source_id": "05FK67",
      "test_category": "Immunochromatographic (lateral flow)"
    },
    {
      "conditions": [],
      "genes": [],
      "manufacturer_or_lab": "Abbott Diagnostics Korea Inc.",
      "marker": "Malaria",
      "name": "Bioline Malaria Ag P.f/P.v",
      "prequalification_year": "2015",
      "region": "who",
      "regulatory_version": "Directive 98/79/EC: Self-declared CE-mark, Annex III",
      "source": "who_ivd",
      "source_id": "05FK80",
      "test_category": "Immunochromatographic (lateral flow)"
    },
    {
      "conditions": [],
      "genes": [],
      "manufacturer_or_lab": "Abbott Diagnostics Korea Inc.",
      "marker": "Malaria",
      "name": "Bioline Malaria Ag P.f/P.v",
      "prequalification_year": "2015",
      "region": "who",
      "regulatory_version": "Directive 98/79/EC: Self-declared CE-mark, Annex III",
      "source": "who_ivd",
      "source_id": "05FK81",
      "test_category": "Immunochromatographic (lateral flow)"
    },
    {
      "conditions": [],
      "genes": [],
      "manufacturer_or_lab": "Abbott Diagnostics Korea Inc.",
      "marker": "Malaria",
      "name": "Bioline Malaria Ag P.f/P.v",
      "prequalification_year": "2015",
      "region": "who",
      "regulatory_version": "Directive 98/79/EC: Self-declared CE-mark, Annex III",
      "source": "who_ivd",
      "source_id": "05FK82",
      "test_category": "Immunochromatographic (lateral flow)"
    },
    {
      "conditions": [],
      "genes": [],
      "manufacturer_or_lab": "Abbott Diagnostics Korea Inc.",
      "marker": "Malaria",
      "name": "Bioline Malaria Ag P.f/P.v",
      "prequalification_year": "2015",
      "region": "who",
      "regulatory_version": "Directive 98/79/EC: Self-declared CE-mark, Annex III",
      "source": "who_ivd",
      "source_id": "05FK83",
      "test_category": "Immunochromatographic (lateral flow)"
    },
    {
      "conditions": [],
      "genes": [],
      "manufacturer_or_lab": "Abbott Diagnostics Korea Inc.",
      "marker": "Malaria",
      "name": "Bioline Malaria Ag P.f/P.v",
      "prequalification_year": "2015",
      "region": "who",
      "regulatory_version": "Directive 98/79/EC: Self-declared CE-mark, Annex III",
      "source": "who_ivd",
      "source_id": "05FK86",
      "test_category": "Immunochromatographic (lateral flow)"
    },
    {
      "conditions": [],
      "genes": [],
      "manufacturer_or_lab": "Abbott Diagnostics Korea Inc.",
      "marker": "Malaria",
      "name": "Bioline Malaria Ag P.f (HRP2/pLDH)",
      "prequalification_year": "2015",
      "region": "who",
      "regulatory_version": "Directive 98/79/EC: Self-declared CE-mark, Annex III",
      "source": "who_ivd",
      "source_id": "05FK90",
      "test_category": "Immunochromatographic (lateral flow)"
    },
    {
      "conditions": [],
      "genes": [],
      "manufacturer_or_lab": "Abbott Diagnostics Korea Inc.",
      "marker": "Malaria",
      "name": "Bioline Malaria Ag P.f (HRP2/pLDH)",
      "prequalification_year": "2015",
      "region": "who",
      "regulatory_version": "Directive 98/79/EC: Self-declared CE-mark, Annex III",
      "source": "who_ivd",
      "source_id": "05FK91",
      "test_category": "Immunochromatographic (lateral flow)"
    },
    {
      "conditions": [],
      "genes": [],
      "manufacturer_or_lab": "Abbott Diagnostics Korea Inc.",
      "marker": "Malaria",
      "name": "Bioline Malaria Ag P.f (HRP2/pLDH)",
      "prequalification_year": "2015",
      "region": "who",
      "regulatory_version": "Directive 98/79/EC: Self-declared CE-mark, Annex III",
      "source": "who_ivd",
      "source_id": "05FK92",
      "test_category": "Immunochromatographic (lateral flow)"
    },
    {
      "conditions": [],
      "genes": [],
      "manufacturer_or_lab": "Abbott Diagnostics Korea Inc.",
      "marker": "Malaria",
      "name": "Bioline Malaria Ag P.f (HRP2/pLDH)",
      "prequalification_year": "2015",
      "region": "who",
      "regulatory_version": "Directive 98/79/EC: Self-declared CE-mark, Annex III",
      "source": "who_ivd",
      "source_id": "05FK93",
      "test_category": "Immunochromatographic (lateral flow)"
    },
    {
      "conditions": [],
      "genes": [],
      "manufacturer_or_lab": "Abbott Diagnostics Korea Inc.",
      "marker": "HIV, Syphilis",
      "name": "Bioline HIV/Syphilis Duo",
      "prequalification_year": "2015",
      "region": "who",
      "regulatory_version": "Rest-of-World",
      "source": "who_ivd",
      "source_id": "06FK30",
      "test_category": "Immunochromatographic (lateral flow)"
    },
    {
      "conditions": [],
      "genes": [],
      "manufacturer_or_lab": "Abbott Diagnostics Korea Inc.",
      "marker": "HIV, Syphilis",
      "name": "Bioline HIV/Syphilis Duo",
      "prequalification_year": "2015",
      "region": "who",
      "regulatory_version": "Rest-of-World",
      "source": "who_ivd",
      "source_id": "06FK35",
      "test_category": "Immunochromatographic (lateral flow)"
    },
    {
      "conditions": [],
      "genes": [],
      "manufacturer_or_lab": "Abbott Diagnostics Korea Inc.",
      "marker": "HIV, Syphilis",
      "name": "Bioline HIV/Syphilis Duo",
      "prequalification_year": "2015",
      "region": "who",
      "regulatory_version": "Rest-of-World",
      "source": "who_ivd",
      "source_id": "06FK37",
      "test_category": "Immunochromatographic (lateral flow)"
    },
    {
      "conditions": [],
      "genes": [],
      "manufacturer_or_lab": "Roche Molecular Systems, Inc.",
      "marker": "HIV",
      "name": "cobas HIV-1 Quantitative nucleic acid test for use on the cobas 5800/6800/8800 Systems",
      "prequalification_year": "2020",
      "region": "who",
      "regulatory_version": "Directive 98/79/EC: Product design examination certificate, Annex IV.4",
      "source": "who_ivd",
      "source_id": "07000995190",
      "test_category": "NAT (nucleic acid testing)"
    },
    {
      "conditions": [],
      "genes": [],
      "manufacturer_or_lab": "Roche Molecular Systems, Inc.",
      "marker": "HIV",
      "name": "COBAS AmpliPrep / COBAS TaqMan HIV-1 Test, version 2.0 (TaqMan 96)",
      "prequalification_year": "2012",
      "region": "who",
      "regulatory_version": "Directive 98/79/EC: Product design examination certificate, Annex IV.4",
      "source": "who_ivd",
      "source_id": "07347308001",
      "test_category": "NAT (nucleic acid testing)"
    },
    {
      "conditions": [],
      "genes": [],
      "manufacturer_or_lab": "Roche Diagnostics GmbH",
      "marker": "HIV",
      "name": "cobas HIV-1 Nucleic acid test for use on the cobas 4800 System",
      "prequalification_year": "2022",
      "region": "who",
      "regulatory_version": "Directive 98/79/EC: Product design examination certificate, Annex IV.4",
      "source": "who_ivd",
      "source_id": "08792992190",
      "test_category": "NAT (nucleic acid testing)"
    },
    {
      "conditions": [],
      "genes": [],
      "manufacturer_or_lab": "Abbott Molecular Inc.",
      "marker": "HIV",
      "name": "Alinity m HIV-1",
      "prequalification_year": "2024",
      "region": "who",
      "regulatory_version": "Directive 98/79/EC: Product design examination certificate, Annex IV.4",
      "source": "who_ivd",
      "source_id": "08N45-090",
      "test_category": "NAT (nucleic acid testing)"
    },
    {
      "conditions": [],
      "genes": [],
      "manufacturer_or_lab": "Abbott Molecular Inc.",
      "marker": "HCV",
      "name": "Alinity m HCV",
      "prequalification_year": "2020",
      "region": "who",
      "regulatory_version": "Directive 98/79/EC: Product design examination certificate, Annex IV.4",
      "source": "who_ivd",
      "source_id": "08N50-080",
      "test_category": "NAT (nucleic acid testing)"
    },
    {
      "conditions": [],
      "genes": [],
      "manufacturer_or_lab": "Abbott Molecular Inc.",
      "marker": "HCV",
      "name": "Alinity m HCV",
      "prequalification_year": "2020",
      "region": "who",
      "regulatory_version": "Directive 98/79/EC: Product design examination certificate, Annex IV.4",
      "source": "who_ivd",
      "source_id": "08N50-090",
      "test_category": "NAT (nucleic acid testing)"
    },
    {
      "conditions": [],
      "genes": [],
      "manufacturer_or_lab": "Abbott Molecular Inc.",
      "marker": "HCV",
      "name": "Alinity m HCV",
      "prequalification_year": "2020",
      "region": "who",
      "regulatory_version": "Directive 98/79/EC: Product design examination certificate, Annex IV.4",
      "source": "who_ivd",
      "source_id": "08N50-70",
      "test_category": "NAT (nucleic acid testing)"
    },
    {
      "conditions": [],
      "genes": [],
      "manufacturer_or_lab": "Roche Molecular Systems, Inc.",
      "marker": "HIV",
      "name": "cobas HIV-1/HIV-2 Qualitative Nucleic acid test for use on the cobas 6800/8800 Systems and cobas HIV-1/HIV-2 Qualitative Nucleic acid test for use on the cobas 5800/6800/8800 Systems",
      "prequalification_year": "2023",
      "region": "who",
      "regulatory_version": "Directive 98/79/EC: Product design examination certificate, Annex IV.4",
      "source": "who_ivd",
      "source_id": "09040528190",
      "test_category": "NAT (nucleic acid testing)"
    },
    {
      "conditions": [],
      "genes": [],
      "manufacturer_or_lab": "Roche Molecular Systems, Inc.",
      "marker": "HIV",
      "name": "cobas HIV-1 Quantitative nucleic acid test for use on the cobas 5800/6800/8800 Systems",
      "prequalification_year": "2020",
      "region": "who",
      "regulatory_version": "Directive 98/79/EC: Product design examination certificate, Annex IV.4",
      "source": "who_ivd",
      "source_id": "09040803190",
      "test_category": "NAT (nucleic acid testing)"
    },
    {
      "conditions": [],
      "genes": [],
      "manufacturer_or_lab": "SD Biosensor, Inc.",
      "marker": "SARS-CoV-2",
      "name": "STANDARD Q COVID-19 Ag Test",
      "prequalification_year": "2025",
      "region": "who",
      "regulatory_version": "Directive 98/79/EC: Self-declared CE-mark, Annex III",
      "source": "who_ivd",
      "source_id": "09COV30D",
      "test_category": "Immunochromatographic (lateral flow)"
    },
    {
      "conditions": [],
      "genes": [],
      "manufacturer_or_lab": "SD Biosensor, Inc.",
      "marker": "SARS-CoV-2",
      "name": "STANDARD Q COVID-19 Ag Test",
      "prequalification_year": "2025",
      "region": "who",
      "regulatory_version": "Directive 98/79/EC: Self-declared CE-mark, Annex III",
      "source": "who_ivd",
      "source_id": "09COV31D",
      "test_category": "Immunochromatographic (lateral flow)"
    },
    {
      "conditions": [],
      "genes": [],
      "manufacturer_or_lab": "SD Biosensor, Inc.",
      "marker": "SARS-CoV-2",
      "name": "STANDARD Q COVID-19 Ag Test",
      "prequalification_year": "2025",
      "region": "who",
      "regulatory_version": "Directive 98/79/EC: Self-declared CE-mark, Annex III",
      "source": "who_ivd",
      "source_id": "09COV32D",
      "test_category": "Immunochromatographic (lateral flow)"
    },
    {
      "conditions": [],
      "genes": [],
      "manufacturer_or_lab": "SD Biosensor, Inc.",
      "marker": "SARS-CoV-2",
      "name": "STANDARD Q COVID-19 Ag Test",
      "prequalification_year": "2025",
      "region": "who",
      "regulatory_version": "Directive 98/79/EC: Self-declared CE-mark, Annex III",
      "source": "who_ivd",
      "source_id": "09COV33D",
      "test_category": "Immunochromatographic (lateral flow)"
    },
    {
      "conditions": [],
      "genes": [],
      "manufacturer_or_lab": "SD Biosensor, Inc.",
      "marker": "HCV",
      "name": "STANDARD Q HCV Ab Test",
      "prequalification_year": "2020",
      "region": "who",
      "regulatory_version": "Rest-of-World",
      "source": "who_ivd",
      "source_id": "09HCV10D",
      "test_category": "Immunochromatographic (lateral flow)"
    },
    {
      "conditions": [],
      "genes": [],
      "manufacturer_or_lab": "SD Biosensor, Inc.",
      "marker": "HIV, Syphilis",
      "name": "STANDARD Q HIV/Syphilis Combo Test",
      "prequalification_year": "2020",
      "region": "who",
      "regulatory_version": "Rest-of-World",
      "source": "who_ivd",
      "source_id": "09HIV20D",
      "test_category": "Immunochromatographic (lateral flow)"
    },
    {
      "conditions": [],
      "genes": [],
      "manufacturer_or_lab": "SD Biosensor, Inc.",
      "marker": "HIV",
      "name": "STANDARD Q HIV 1/2 Ab 3-Line Test",
      "prequalification_year": "2020",
      "region": "who",
      "regulatory_version": "Rest-of-World",
      "source": "who_ivd",
      "source_id": "09HIV30D",
      "test_category": "Immunochromatographic (lateral flow)"
    },
    {
      "conditions": [],
      "genes": [],
      "manufacturer_or_lab": "SD Biosensor, Inc.",
      "marker": "HIV",
      "name": "STANDARD Q HIV 1/2 Ab 3-Line Test",
      "prequalification_year": "2020",
      "region": "who",
      "regulatory_version": "Rest-of-World",
      "source": "who_ivd",
      "source_id": "09HIV30DM",
      "test_category": "Immunochromatographic (lateral flow)"
    },
    {
      "conditions": [],
      "genes": [],
      "manufacturer_or_lab": "SD Biosensor, Inc.",
      "marker": "Malaria",
      "name": "STANDARD Q Malaria P.f Ag Test",
      "prequalification_year": "2020",
      "region": "who",
      "regulatory_version": "Directive 98/79/EC: Self-declared CE-mark, Annex III",
      "source": "who_ivd",
      "source_id": "09MAL10D",
      "test_category": "Immunochromatographic (lateral flow)"
    },
    {
      "conditions": [],
      "genes": [],
      "manufacturer_or_lab": "SD Biosensor, Inc.",
      "marker": "Malaria",
      "name": "STANDARD Q Malaria P.f/P.v Ag Test",
      "prequalification_year": "2020",
      "region": "who",
      "regulatory_version": "Directive 98/79/EC: Self-declared CE-mark, Annex III",
      "source": "who_ivd",
      "source_id": "09MAL20D",
      "test_category": "Immunochromatographic (lateral flow)"
    },
    {
      "conditions": [],
      "genes": [],
      "manufacturer_or_lab": "SD Biosensor, Inc.",
      "marker": "Malaria",
      "name": "STANDARD Q Malaria P.f/Pan Ag Test",
      "prequalification_year": "2020",
      "region": "who",
      "regulatory_version": "Directive 98/79/EC: Self-declared CE-mark, Annex III",
      "source": "who_ivd",
      "source_id": "09MAL30D",
      "test_category": "Immunochromatographic (lateral flow)"
    },
    {
      "conditions": [],
      "genes": [
        "HR"
      ],
      "manufacturer_or_lab": "Abbott Molecular Inc.",
      "marker": "HPV",
      "name": "Alinity m HR HPV",
      "prequalification_year": "2025",
      "region": "who",
      "regulatory_version": "Directive 98/79/EC: Self-declared CE-mark, Annex III",
      "source": "who_ivd",
      "source_id": "09N15-080",
      "test_category": "NAT - PCR"
    },
    {
      "conditions": [],
      "genes": [
        "HR"
      ],
      "manufacturer_or_lab": "Abbott Molecular Inc.",
      "marker": "HPV",
      "name": "Alinity m HR HPV",
      "prequalification_year": "2025",
      "region": "who",
      "regulatory_version": "Directive 98/79/EC: Self-declared CE-mark, Annex III",
      "source": "who_ivd",
      "source_id": "09N15-090",
      "test_category": "NAT - PCR"
    },
    {
      "conditions": [],
      "genes": [
        "HR"
      ],
      "manufacturer_or_lab": "Abbott Molecular Inc.",
      "marker": "HPV",
      "name": "Alinity m HR HPV",
      "prequalification_year": "2025",
      "region": "who",
      "regulatory_version": "Directive 98/79/EC: Self-declared CE-mark, Annex III",
      "source": "who_ivd",
      "source_id": "09N15-092",
      "test_category": "NAT - PCR"
    },
    {
      "conditions": [],
      "genes": [
        "KIT"
      ],
      "manufacturer_or_lab": "OraSure Technologies, Inc.",
      "marker": "HCV",
      "name": "OraQuick HCV Rapid Antibody Test Kit",
      "prequalification_year": "2024",
      "region": "who",
      "regulatory_version": "Directive 98/79/EC: Full quality assurance certificate, Annex IV.3",
      "source": "who_ivd",
      "source_id": "1001-0270",
      "test_category": "Immunochromatographic (lateral flow)"
    },
    {
      "conditions": [],
      "genes": [
        "KIT"
      ],
      "manufacturer_or_lab": "OraSure Technologies, Inc.",
      "marker": "HCV",
      "name": "OraQuick HCV Rapid Antibody Test Kit",
      "prequalification_year": "2024",
      "region": "who",
      "regulatory_version": "Directive 98/79/EC: Full quality assurance certificate, Annex IV.3",
      "source": "who_ivd",
      "source_id": "1001-0274",
      "test_category": "Immunochromatographic (lateral flow)"
    },
    {
      "conditions": [],
      "genes": [],
      "manufacturer_or_lab": "SD Biosensor, Inc.",
      "marker": "SARS-CoV-2",
      "name": "STANDARD Q COVID-19 Ag Test",
      "prequalification_year": "2025",
      "region": "who",
      "regulatory_version": "Directive 98/79/EC: Self-declared CE-mark, Annex III",
      "source": "who_ivd",
      "source_id": "10COVC11",
      "test_category": "Immunochromatographic (lateral flow)"
    },
    {
      "conditions": [],
      "genes": [],
      "manufacturer_or_lab": "MP Biomedicals Asia Pacific Pte.Ltd.",
      "marker": "HIV",
      "name": "MP Diagnostics HIV Blot 2.2",
      "prequalification_year": "2016",
      "region": "who",
      "regulatory_version": "Directive 98/79/EC: Product design examination certificate, Annex IV.4",
      "source": "who_ivd",
      "source_id": "11030-018",
      "test_category": "IA - Immunoblot"
    },
    {
      "conditions": [],
      "genes": [],
      "manufacturer_or_lab": "MP Biomedicals Asia Pacific Pte.Ltd.",
      "marker": "HIV",
      "name": "MP Diagnostics HIV Blot 2.2",
      "prequalification_year": "2016",
      "region": "who",
      "regulatory_version": "Directive 98/79/EC: Product design examination certificate, Annex IV.4",
      "source": "who_ivd",
      "source_id": "11030-036",
      "test_category": "IA - Immunoblot"
    },
    {
      "conditions": [],
      "genes": [],
      "manufacturer_or_lab": "Trinity Biotech Manufacturing Ltd",
      "marker": "HIV",
      "name": "Uni-Gold HIV",
      "prequalification_year": "2012",
      "region": "who",
      "regulatory_version": "Rest-of-World",
      "source": "who_ivd",
      "source_id": "1206502",
      "test_category": "Immunochromatographic (lateral flow)"
    },
    {
      "conditions": [],
      "genes": [],
      "manufacturer_or_lab": "Trinity Biotech Manufacturing Ltd",
      "marker": "HIV",
      "name": "Uni-Gold HIV",
      "prequalification_year": "2012",
      "region": "who",
      "regulatory_version": "Rest-of-World",
      "source": "who_ivd",
      "source_id": "1206502E",
      "test_category": "Immunochromatographic (lateral flow)"
    }
  ],
  "sample_size": 100,
  "source": "who_ivd"
}
